bing_image_search_mcp/__init__.py
bing_image_search_mcp/server.py
bing_image_search_mcp-0.0.6.dist-info/METADATA
bing_image_search_mcp-0.0.6.dist-info/WHEEL
bing_image_search_mcp-0.0.6.dist-info/entry_points.txt
bing_image_search_mcp-0.0.6.dist-info/top_level.txt
bing_image_search_mcp-0.0.6.dist-info/RECORD
