Metadata-Version: 2.4
Name: bing-image-search-mcp
Version: 0.0.6
Summary: Bing Image Search MCP Server without Access Keys, Provides Bing Image Search Results to AI Agents
Author-email: aihubadmin@126.com
License: MIT License
Project-URL: Homepage, https://www.deepnlp.org/store/ai-agent/mcp-server
Project-URL: Repository, https://github.com/AI-Agent-Hub/AI-Agent-Marketplace
Keywords: Bing Search,Bing Image Search,MCP,API,AI Agent
Classifier: Development Status :: 3 - Alpha
Classifier: Intended Audience :: Developers
Classifier: Topic :: Software Development :: Build Tools
Classifier: License :: OSI Approved :: MIT License
Requires-Python: >=3.10
Requires-Dist: httpx>=0.28.1
Requires-Dist: mcp[cli]>=1.9.4
Requires-Dist: requests>=2.17.0
Requires-Dist: beautifulsoup4>=4.0.1
Requires-Dist: urllib3>=2.0.0
Requires-Dist: logging>=0.4.9
Requires-Dist: pydantic>=2.11.7
